<?xml version='1.0' encoding='UTF-8'?>
<document filename="cTDaR_t00665.jpg">
  <table>
    <Coords points="52,45 4712,45 4712,3854 52,3854"/>
    <cell start-row="0" end-row="0" start-col="0" end-col="0">
      <Coords points="52,45 31,67 21,86 14,107 16,470 19,477 18,501 167,501 166,46"/>
    </cell>
    <cell start-row="0" end-row="0" start-col="1" end-col="1">
      <Coords points="166,46 167,501 179,501 357,503 400,503 399,48"/>
    </cell>
    <cell start-row="0" end-row="0" start-col="2" end-col="2">
      <Coords points="399,48 400,503 682,506 804,509 1190,513 1188,47 836,50 442,49"/>
    </cell>
    <cell start-row="0" end-row="0" start-col="3" end-col="3">
      <Coords points="1188,47 1190,513 1350,515 1349,41 1333,41 1311,45 1247,47"/>
    </cell>
    <cell start-row="0" end-row="0" start-col="4" end-col="4">
      <Coords points="1349,41 1350,515 1491,517 1606,517 1847,518 1848,33 1746,34 1667,40 1527,37 1420,42"/>
    </cell>
    <cell start-row="0" end-row="0" start-col="5" end-col="5">
      <Coords points="1848,33 1847,518 2007,519 2319,519 2373,522 2394,522 2395,25 2367,24 2127,31 1898,33"/>
    </cell>
    <cell start-row="0" end-row="0" start-col="6" end-col="6">
      <Coords points="2395,25 2394,522 2414,523 2664,518 2741,519 2973,519 2977,39 2940,37 2714,33 2438,27"/>
    </cell>
    <cell start-row="0" end-row="0" start-col="7" end-col="7">
      <Coords points="2977,39 2973,519 3031,519 3254,518 3467,517 3485,517 3487,47 3429,48 3388,45 3147,43 3022,43"/>
    </cell>
    <cell start-row="0" end-row="0" start-col="8" end-col="8">
      <Coords points="3487,47 3485,517 3555,520 3662,518 4012,519 4015,56 3773,52 3575,47"/>
    </cell>
    <cell start-row="0" end-row="0" start-col="9" end-col="9">
      <Coords points="4015,56 4012,519 4769,522 4774,237 4779,92 4778,77 4770,68 4759,62 4441,61 4241,59 4055,57"/>
    </cell>
    <cell start-row="1" end-row="1" start-col="0" end-col="0">
      <Coords points="18,501 17,591 17,603 167,605 167,501"/>
    </cell>
    <cell start-row="1" end-row="1" start-col="1" end-col="1">
      <Coords points="167,501 167,605 400,608 400,503 357,503 179,501"/>
    </cell>
    <cell start-row="1" end-row="1" start-col="2" end-col="2">
      <Coords points="400,503 400,608 819,615 1191,629 1190,513 804,509 682,506"/>
    </cell>
    <cell start-row="1" end-row="1" start-col="3" end-col="3">
      <Coords points="1190,513 1191,629 1252,632 1350,634 1350,515"/>
    </cell>
    <cell start-row="1" end-row="1" start-col="4" end-col="4">
      <Coords points="1350,515 1350,634 1846,648 1847,518 1606,517 1491,517"/>
    </cell>
    <cell start-row="1" end-row="1" start-col="5" end-col="5">
      <Coords points="1847,518 1846,648 2164,658 2394,653 2394,522 2373,522 2319,519 2007,519"/>
    </cell>
    <cell start-row="1" end-row="1" start-col="6" end-col="6">
      <Coords points="2394,522 2394,653 2711,647 2973,642 2973,519 2741,519 2664,518 2414,523"/>
    </cell>
    <cell start-row="1" end-row="1" start-col="7" end-col="7">
      <Coords points="2973,519 2973,642 3485,632 3485,517 3467,517 3254,518 3031,519"/>
    </cell>
    <cell start-row="1" end-row="1" start-col="8" end-col="8">
      <Coords points="3485,517 3485,632 3768,628 4012,621 4012,519 3662,518 3555,520"/>
    </cell>
    <cell start-row="1" end-row="1" start-col="9" end-col="9">
      <Coords points="4012,519 4012,621 4768,603 4769,522"/>
    </cell>
    <cell start-row="2" end-row="2" start-col="0" end-col="0">
      <Coords points="17,603 21,668 17,702 167,703 167,605"/>
    </cell>
    <cell start-row="2" end-row="2" start-col="1" end-col="1">
      <Coords points="167,605 167,703 399,705 400,608"/>
    </cell>
    <cell start-row="2" end-row="2" start-col="2" end-col="2">
      <Coords points="400,608 399,705 1191,712 1191,629 819,615"/>
    </cell>
    <cell start-row="2" end-row="2" start-col="3" end-col="3">
      <Coords points="1191,629 1191,712 1350,713 1350,634 1252,632"/>
    </cell>
    <cell start-row="2" end-row="2" start-col="4" end-col="4">
      <Coords points="1350,634 1350,713 1845,731 1846,648"/>
    </cell>
    <cell start-row="2" end-row="2" start-col="5" end-col="5">
      <Coords points="1846,648 1845,731 2393,736 2394,653 2164,658"/>
    </cell>
    <cell start-row="2" end-row="2" start-col="6" end-col="6">
      <Coords points="2394,653 2393,736 2973,729 2973,642 2711,647"/>
    </cell>
    <cell start-row="2" end-row="2" start-col="7" end-col="7">
      <Coords points="2973,642 2973,729 3485,735 3485,632"/>
    </cell>
    <cell start-row="2" end-row="2" start-col="8" end-col="8">
      <Coords points="3485,632 3485,735 3731,738 4012,728 4012,621 3768,628"/>
    </cell>
    <cell start-row="2" end-row="2" start-col="9" end-col="9">
      <Coords points="4012,621 4012,728 4765,702 4768,610 4768,603"/>
    </cell>
    <cell start-row="3" end-row="3" start-col="0" end-col="0">
      <Coords points="17,702 17,709 19,783 19,790 167,789 167,703"/>
    </cell>
    <cell start-row="3" end-row="3" start-col="1" end-col="1">
      <Coords points="167,703 167,789 318,788 399,802 399,705"/>
    </cell>
    <cell start-row="3" end-row="3" start-col="2" end-col="2">
      <Coords points="399,705 399,802 493,820 1009,821 1192,820 1191,712"/>
    </cell>
    <cell start-row="3" end-row="3" start-col="3" end-col="3">
      <Coords points="1191,712 1192,820 1299,820 1351,820 1350,713"/>
    </cell>
    <cell start-row="3" end-row="3" start-col="4" end-col="4">
      <Coords points="1350,713 1351,820 1844,828 1845,731"/>
    </cell>
    <cell start-row="3" end-row="3" start-col="5" end-col="5">
      <Coords points="1845,731 1844,828 2163,834 2393,826 2393,736"/>
    </cell>
    <cell start-row="3" end-row="3" start-col="6" end-col="6">
      <Coords points="2393,736 2393,826 2942,807 2973,806 2973,729"/>
    </cell>
    <cell start-row="3" end-row="3" start-col="7" end-col="7">
      <Coords points="2973,729 2973,806 3485,801 3485,735"/>
    </cell>
    <cell start-row="3" end-row="3" start-col="8" end-col="8">
      <Coords points="3485,735 3485,801 4012,796 4012,728 3731,738"/>
    </cell>
    <cell start-row="3" end-row="3" start-col="9" end-col="9">
      <Coords points="4012,728 4012,796 4765,790 4765,714 4765,702"/>
    </cell>
    <cell start-row="4" end-row="4" start-col="0" end-col="0">
      <Coords points="19,790 21,832 21,892 168,894 167,789"/>
    </cell>
    <cell start-row="4" end-row="4" start-col="1" end-col="1">
      <Coords points="167,789 168,894 399,898 399,802 318,788"/>
    </cell>
    <cell start-row="4" end-row="4" start-col="2" end-col="2">
      <Coords points="399,802 399,898 758,905 1192,929 1192,820 1009,821 493,820"/>
    </cell>
    <cell start-row="4" end-row="4" start-col="3" end-col="3">
      <Coords points="1192,820 1192,929 1352,929 1351,820 1299,820"/>
    </cell>
    <cell start-row="4" end-row="4" start-col="4" end-col="4">
      <Coords points="1351,820 1352,929 1847,941 1844,828"/>
    </cell>
    <cell start-row="4" end-row="4" start-col="5" end-col="5">
      <Coords points="1844,828 1847,941 2393,937 2393,826 2163,834"/>
    </cell>
    <cell start-row="4" end-row="4" start-col="6" end-col="6">
      <Coords points="2393,826 2393,937 2973,915 2973,806 2942,807"/>
    </cell>
    <cell start-row="4" end-row="4" start-col="7" end-col="7">
      <Coords points="2973,806 2973,915 3485,894 3485,801"/>
    </cell>
    <cell start-row="4" end-row="4" start-col="8" end-col="8">
      <Coords points="3485,801 3485,894 4012,893 4012,796"/>
    </cell>
    <cell start-row="4" end-row="4" start-col="9" end-col="9">
      <Coords points="4012,796 4012,893 4763,892 4765,829 4765,790"/>
    </cell>
    <cell start-row="5" end-row="5" start-col="0" end-col="0">
      <Coords points="21,892 22,951 24,968 24,996 170,996 168,894"/>
    </cell>
    <cell start-row="5" end-row="5" start-col="1" end-col="1">
      <Coords points="168,894 170,996 400,996 399,898"/>
    </cell>
    <cell start-row="5" end-row="5" start-col="2" end-col="2">
      <Coords points="399,898 400,996 774,998 1192,1012 1192,929 758,905"/>
    </cell>
    <cell start-row="5" end-row="5" start-col="3" end-col="3">
      <Coords points="1192,929 1192,1012 1352,1017 1352,929"/>
    </cell>
    <cell start-row="5" end-row="5" start-col="4" end-col="4">
      <Coords points="1352,929 1352,1017 1460,1022 1844,1023 1847,941"/>
    </cell>
    <cell start-row="5" end-row="5" start-col="5" end-col="5">
      <Coords points="1847,941 1844,1023 2393,1026 2393,937"/>
    </cell>
    <cell start-row="5" end-row="5" start-col="6" end-col="6">
      <Coords points="2393,937 2393,1026 2575,1027 2972,1021 2973,915"/>
    </cell>
    <cell start-row="5" end-row="5" start-col="7" end-col="7">
      <Coords points="2973,915 2972,1021 3486,1013 3485,894"/>
    </cell>
    <cell start-row="5" end-row="5" start-col="8" end-col="8">
      <Coords points="3485,894 3486,1013 4012,1005 4012,893"/>
    </cell>
    <cell start-row="5" end-row="5" start-col="9" end-col="9">
      <Coords points="4012,893 4012,1005 4762,996 4763,892"/>
    </cell>
    <cell start-row="6" end-row="6" start-col="0" end-col="0">
      <Coords points="24,996 24,1051 24,1080 24,1089 170,1090 170,996"/>
    </cell>
    <cell start-row="6" end-row="6" start-col="1" end-col="1">
      <Coords points="170,996 170,1090 400,1092 399,996"/>
    </cell>
    <cell start-row="6" end-row="6" start-col="2" end-col="2">
      <Coords points="399,996 400,1092 1085,1100 1192,1100 1192,1012 774,998"/>
    </cell>
    <cell start-row="6" end-row="6" start-col="3" end-col="3">
      <Coords points="1192,1012 1192,1100 1352,1100 1352,1017"/>
    </cell>
    <cell start-row="6" end-row="6" start-col="4" end-col="4">
      <Coords points="1352,1017 1352,1100 1587,1102 1844,1109 1844,1023 1460,1022"/>
    </cell>
    <cell start-row="6" end-row="6" start-col="5" end-col="5">
      <Coords points="1844,1023 1844,1109 2248,1122 2392,1129 2393,1026"/>
    </cell>
    <cell start-row="6" end-row="6" start-col="6" end-col="6">
      <Coords points="2393,1026 2392,1129 2503,1136 2595,1125 2804,1129 2972,1125 2972,1021 2575,1027"/>
    </cell>
    <cell start-row="6" end-row="6" start-col="7" end-col="7">
      <Coords points="2972,1021 2972,1125 3486,1114 3486,1013"/>
    </cell>
    <cell start-row="6" end-row="6" start-col="8" end-col="8">
      <Coords points="3486,1013 3486,1114 4012,1103 4012,1005"/>
    </cell>
    <cell start-row="6" end-row="6" start-col="9" end-col="9">
      <Coords points="4012,1005 4012,1103 4758,1089 4762,997 4762,996"/>
    </cell>
    <cell start-row="7" end-row="7" start-col="0" end-col="0">
      <Coords points="24,1089 26,1183 26,1201 171,1201 170,1090"/>
    </cell>
    <cell start-row="7" end-row="7" start-col="1" end-col="1">
      <Coords points="170,1090 171,1201 399,1202 400,1092"/>
    </cell>
    <cell start-row="7" end-row="7" start-col="2" end-col="2">
      <Coords points="400,1092 399,1202 518,1203 795,1209 1070,1210 1192,1210 1192,1100 1085,1100"/>
    </cell>
    <cell start-row="7" end-row="7" start-col="3" end-col="3">
      <Coords points="1192,1100 1192,1210 1353,1210 1352,1100"/>
    </cell>
    <cell start-row="7" end-row="7" start-col="4" end-col="4">
      <Coords points="1352,1100 1353,1210 1487,1210 1844,1220 1844,1109 1587,1102"/>
    </cell>
    <cell start-row="7" end-row="7" start-col="5" end-col="5">
      <Coords points="1844,1109 1844,1220 2241,1233 2391,1231 2392,1129 2248,1122"/>
    </cell>
    <cell start-row="7" end-row="7" start-col="6" end-col="6">
      <Coords points="2392,1129 2391,1231 2742,1228 2972,1224 2972,1125 2804,1129 2595,1125 2503,1136"/>
    </cell>
    <cell start-row="7" end-row="7" start-col="7" end-col="7">
      <Coords points="2972,1125 2972,1224 3486,1217 3486,1114"/>
    </cell>
    <cell start-row="7" end-row="7" start-col="8" end-col="8">
      <Coords points="3486,1114 3486,1217 4011,1210 4012,1103"/>
    </cell>
    <cell start-row="7" end-row="7" start-col="9" end-col="9">
      <Coords points="4012,1103 4011,1210 4757,1201 4757,1137 4758,1089"/>
    </cell>
    <cell start-row="8" end-row="8" start-col="0" end-col="0">
      <Coords points="26,1201 28,1259 27,1291 171,1294 171,1201"/>
    </cell>
    <cell start-row="8" end-row="8" start-col="1" end-col="1">
      <Coords points="171,1201 171,1294 399,1299 399,1202"/>
    </cell>
    <cell start-row="8" end-row="8" start-col="2" end-col="2">
      <Coords points="399,1202 399,1299 1192,1318 1192,1210 1070,1210 795,1209 518,1203"/>
    </cell>
    <cell start-row="8" end-row="8" start-col="3" end-col="3">
      <Coords points="1192,1210 1192,1318 1353,1322 1353,1210"/>
    </cell>
    <cell start-row="8" end-row="8" start-col="4" end-col="4">
      <Coords points="1353,1210 1353,1322 1462,1325 1707,1331 1845,1326 1844,1220 1487,1210"/>
    </cell>
    <cell start-row="8" end-row="8" start-col="5" end-col="5">
      <Coords points="1844,1220 1845,1326 2217,1314 2391,1314 2391,1231 2241,1233"/>
    </cell>
    <cell start-row="8" end-row="8" start-col="6" end-col="6">
      <Coords points="2391,1231 2391,1314 2937,1314 2972,1313 2972,1224 2742,1228"/>
    </cell>
    <cell start-row="8" end-row="8" start-col="7" end-col="7">
      <Coords points="2972,1224 2972,1313 3486,1306 3486,1217"/>
    </cell>
    <cell start-row="8" end-row="8" start-col="8" end-col="8">
      <Coords points="3486,1217 3486,1306 4011,1299 4011,1210"/>
    </cell>
    <cell start-row="8" end-row="8" start-col="9" end-col="9">
      <Coords points="4011,1210 4011,1299 4758,1291 4757,1201"/>
    </cell>
    <cell start-row="9" end-row="9" start-col="0" end-col="0">
      <Coords points="27,1291 27,1362 30,1370 27,1385 29,1389 170,1392 171,1294"/>
    </cell>
    <cell start-row="9" end-row="9" start-col="1" end-col="1">
      <Coords points="171,1294 170,1392 399,1398 399,1299"/>
    </cell>
    <cell start-row="9" end-row="9" start-col="2" end-col="2">
      <Coords points="399,1299 399,1398 1192,1421 1192,1318"/>
    </cell>
    <cell start-row="9" end-row="9" start-col="3" end-col="3">
      <Coords points="1192,1318 1192,1421 1351,1426 1354,1426 1353,1322"/>
    </cell>
    <cell start-row="9" end-row="9" start-col="4" end-col="4">
      <Coords points="1353,1322 1354,1426 1845,1430 1845,1326 1707,1331 1462,1325"/>
    </cell>
    <cell start-row="9" end-row="9" start-col="5" end-col="5">
      <Coords points="1845,1326 1845,1430 2281,1434 2390,1438 2391,1314 2217,1314"/>
    </cell>
    <cell start-row="9" end-row="9" start-col="6" end-col="6">
      <Coords points="2391,1314 2390,1438 2591,1448 2973,1442 2972,1313 2937,1314"/>
    </cell>
    <cell start-row="9" end-row="9" start-col="7" end-col="7">
      <Coords points="2972,1313 2973,1442 3486,1435 3486,1306"/>
    </cell>
    <cell start-row="9" end-row="9" start-col="8" end-col="8">
      <Coords points="3486,1306 3486,1435 3723,1432 4010,1420 4011,1299"/>
    </cell>
    <cell start-row="9" end-row="9" start-col="9" end-col="9">
      <Coords points="4011,1299 4010,1420 4757,1389 4759,1314 4758,1291"/>
    </cell>
    <cell start-row="10" end-row="10" start-col="0" end-col="0">
      <Coords points="29,1389 32,1395 27,1443 27,1466 26,1482 169,1485 170,1392"/>
    </cell>
    <cell start-row="10" end-row="10" start-col="1" end-col="1">
      <Coords points="170,1392 169,1485 399,1489 399,1398"/>
    </cell>
    <cell start-row="10" end-row="10" start-col="2" end-col="2">
      <Coords points="399,1398 399,1489 543,1493 716,1494 1192,1511 1192,1421"/>
    </cell>
    <cell start-row="10" end-row="10" start-col="3" end-col="3">
      <Coords points="1192,1421 1192,1511 1354,1517 1354,1426 1351,1426"/>
    </cell>
    <cell start-row="10" end-row="10" start-col="4" end-col="4">
      <Coords points="1354,1426 1354,1517 1504,1523 1845,1527 1845,1430"/>
    </cell>
    <cell start-row="10" end-row="10" start-col="5" end-col="5">
      <Coords points="1845,1430 1845,1527 2295,1534 2390,1538 2390,1438 2281,1434"/>
    </cell>
    <cell start-row="10" end-row="10" start-col="6" end-col="6">
      <Coords points="2390,1438 2390,1538 2565,1547 2755,1542 2973,1537 2973,1442 2591,1448"/>
    </cell>
    <cell start-row="10" end-row="10" start-col="7" end-col="7">
      <Coords points="2973,1442 2973,1537 3487,1527 3486,1435"/>
    </cell>
    <cell start-row="10" end-row="10" start-col="8" end-col="8">
      <Coords points="3486,1435 3487,1527 3828,1522 4010,1514 4010,1420 3723,1432"/>
    </cell>
    <cell start-row="10" end-row="10" start-col="9" end-col="9">
      <Coords points="4010,1420 4010,1514 4752,1482 4753,1469 4757,1394 4757,1389"/>
    </cell>
    <cell start-row="11" end-row="11" start-col="0" end-col="0">
      <Coords points="26,1482 25,1499 29,1554 27,1577 169,1577 169,1485"/>
    </cell>
    <cell start-row="11" end-row="11" start-col="1" end-col="1">
      <Coords points="169,1485 169,1577 398,1579 399,1489"/>
    </cell>
    <cell start-row="11" end-row="11" start-col="2" end-col="2">
      <Coords points="399,1489 398,1579 467,1580 864,1599 1051,1600 1193,1613 1192,1511 716,1494 543,1493"/>
    </cell>
    <cell start-row="11" end-row="11" start-col="3" end-col="3">
      <Coords points="1192,1511 1193,1613 1216,1616 1354,1616 1354,1517"/>
    </cell>
    <cell start-row="11" end-row="11" start-col="4" end-col="4">
      <Coords points="1354,1517 1354,1616 1576,1616 1845,1616 1845,1527 1504,1523"/>
    </cell>
    <cell start-row="11" end-row="11" start-col="5" end-col="5">
      <Coords points="1845,1527 1845,1616 2389,1617 2390,1538 2295,1534"/>
    </cell>
    <cell start-row="11" end-row="11" start-col="6" end-col="6">
      <Coords points="2390,1538 2389,1617 2639,1618 2973,1626 2973,1537 2755,1542 2565,1547"/>
    </cell>
    <cell start-row="11" end-row="11" start-col="7" end-col="7">
      <Coords points="2973,1537 2973,1626 3489,1640 3487,1527"/>
    </cell>
    <cell start-row="11" end-row="11" start-col="8" end-col="8">
      <Coords points="3487,1527 3489,1640 3595,1643 3821,1647 3972,1637 4010,1634 4010,1514 3828,1522"/>
    </cell>
    <cell start-row="11" end-row="11" start-col="9" end-col="9">
      <Coords points="4010,1514 4010,1634 4751,1577 4751,1518 4752,1482"/>
    </cell>
    <cell start-row="12" end-row="12" start-col="0" end-col="0">
      <Coords points="27,1577 27,1587 30,1657 29,1679 170,1679 169,1577"/>
    </cell>
    <cell start-row="12" end-row="12" start-col="1" end-col="1">
      <Coords points="169,1577 170,1679 398,1681 398,1579"/>
    </cell>
    <cell start-row="12" end-row="12" start-col="2" end-col="2">
      <Coords points="398,1579 398,1681 486,1682 915,1702 1192,1715 1193,1613 1051,1600 864,1599 467,1580"/>
    </cell>
    <cell start-row="12" end-row="12" start-col="3" end-col="3">
      <Coords points="1193,1613 1192,1715 1354,1723 1354,1616 1216,1616"/>
    </cell>
    <cell start-row="12" end-row="12" start-col="4" end-col="4">
      <Coords points="1354,1616 1354,1723 1655,1738 1844,1734 1845,1616 1576,1616"/>
    </cell>
    <cell start-row="12" end-row="12" start-col="5" end-col="5">
      <Coords points="1845,1616 1844,1734 2388,1723 2389,1617"/>
    </cell>
    <cell start-row="12" end-row="12" start-col="6" end-col="6">
      <Coords points="2389,1617 2388,1723 2973,1712 2973,1626 2639,1618"/>
    </cell>
    <cell start-row="12" end-row="12" start-col="7" end-col="7">
      <Coords points="2973,1626 2973,1712 3489,1702 3489,1640"/>
    </cell>
    <cell start-row="12" end-row="12" start-col="8" end-col="8">
      <Coords points="3489,1640 3489,1702 4010,1692 4010,1634 3972,1637 3821,1647 3595,1643"/>
    </cell>
    <cell start-row="12" end-row="12" start-col="9" end-col="9">
      <Coords points="4010,1634 4010,1692 4750,1679 4751,1608 4751,1577"/>
    </cell>
    <cell start-row="13" end-row="13" start-col="0" end-col="0">
      <Coords points="29,1679 28,1750 29,1778 170,1783 170,1679"/>
    </cell>
    <cell start-row="13" end-row="13" start-col="1" end-col="1">
      <Coords points="170,1679 170,1783 398,1791 398,1681"/>
    </cell>
    <cell start-row="13" end-row="13" start-col="2" end-col="2">
      <Coords points="398,1681 398,1791 472,1794 718,1802 936,1806 1097,1813 1192,1815 1192,1715 915,1702 486,1682"/>
    </cell>
    <cell start-row="13" end-row="13" start-col="3" end-col="3">
      <Coords points="1192,1715 1192,1815 1354,1819 1354,1723"/>
    </cell>
    <cell start-row="13" end-row="13" start-col="4" end-col="4">
      <Coords points="1354,1723 1354,1819 1583,1825 1844,1826 1844,1734 1655,1738"/>
    </cell>
    <cell start-row="13" end-row="13" start-col="5" end-col="5">
      <Coords points="1844,1734 1844,1826 2205,1828 2388,1827 2388,1723"/>
    </cell>
    <cell start-row="13" end-row="13" start-col="6" end-col="6">
      <Coords points="2388,1723 2388,1827 2648,1826 2973,1818 2973,1712"/>
    </cell>
    <cell start-row="13" end-row="13" start-col="7" end-col="7">
      <Coords points="2973,1712 2973,1818 3489,1806 3489,1702"/>
    </cell>
    <cell start-row="13" end-row="13" start-col="8" end-col="8">
      <Coords points="3489,1702 3489,1806 4010,1794 4010,1692"/>
    </cell>
    <cell start-row="13" end-row="13" start-col="9" end-col="9">
      <Coords points="4010,1692 4010,1794 4749,1778 4750,1742 4750,1679"/>
    </cell>
    <cell start-row="14" end-row="14" start-col="0" end-col="0">
      <Coords points="29,1778 34,1842 32,1878 170,1878 170,1783"/>
    </cell>
    <cell start-row="14" end-row="14" start-col="1" end-col="1">
      <Coords points="170,1783 170,1878 398,1878 398,1791"/>
    </cell>
    <cell start-row="14" end-row="14" start-col="2" end-col="2">
      <Coords points="398,1791 398,1878 523,1879 794,1906 1192,1923 1192,1815 1097,1813 936,1806 718,1802 472,1794"/>
    </cell>
    <cell start-row="14" end-row="14" start-col="3" end-col="3">
      <Coords points="1192,1815 1192,1923 1241,1926 1354,1927 1354,1819"/>
    </cell>
    <cell start-row="14" end-row="14" start-col="4" end-col="4">
      <Coords points="1354,1819 1354,1927 1459,1928 1645,1923 1844,1920 1844,1826 1583,1825"/>
    </cell>
    <cell start-row="14" end-row="14" start-col="5" end-col="5">
      <Coords points="1844,1826 1844,1920 2388,1914 2388,1827 2205,1828"/>
    </cell>
    <cell start-row="14" end-row="14" start-col="6" end-col="6">
      <Coords points="2388,1827 2388,1914 2390,1914 2974,1905 2973,1818 2648,1826"/>
    </cell>
    <cell start-row="14" end-row="14" start-col="7" end-col="7">
      <Coords points="2973,1818 2974,1905 3489,1897 3489,1806"/>
    </cell>
    <cell start-row="14" end-row="14" start-col="8" end-col="8">
      <Coords points="3489,1806 3489,1897 4010,1889 4010,1794"/>
    </cell>
    <cell start-row="14" end-row="14" start-col="9" end-col="9">
      <Coords points="4010,1794 4010,1889 4748,1878 4748,1829 4749,1778"/>
    </cell>
    <cell start-row="15" end-row="15" start-col="0" end-col="0">
      <Coords points="32,1878 32,1894 35,1949 34,1979 171,1976 170,1878"/>
    </cell>
    <cell start-row="15" end-row="15" start-col="1" end-col="1">
      <Coords points="170,1878 171,1976 399,1973 398,1878"/>
    </cell>
    <cell start-row="15" end-row="15" start-col="2" end-col="2">
      <Coords points="398,1878 399,1973 503,1972 720,1996 862,2018 1192,2015 1192,1923 794,1906 523,1879"/>
    </cell>
    <cell start-row="15" end-row="15" start-col="3" end-col="3">
      <Coords points="1192,1923 1192,2015 1354,2013 1354,1927 1241,1926"/>
    </cell>
    <cell start-row="15" end-row="15" start-col="4" end-col="4">
      <Coords points="1354,1927 1354,2013 1565,2012 1844,2014 1844,1920 1645,1923 1459,1928"/>
    </cell>
    <cell start-row="15" end-row="15" start-col="5" end-col="5">
      <Coords points="1844,1920 1844,2014 2277,2019 2388,2019 2388,1914"/>
    </cell>
    <cell start-row="15" end-row="15" start-col="6" end-col="6">
      <Coords points="2388,1914 2388,2019 2974,2022 2974,1905 2390,1914"/>
    </cell>
    <cell start-row="15" end-row="15" start-col="7" end-col="7">
      <Coords points="2974,1905 2974,2022 3016,2023 3489,2018 3489,1897"/>
    </cell>
    <cell start-row="15" end-row="15" start-col="8" end-col="8">
      <Coords points="3489,1897 3489,2018 3720,2016 4010,2005 4010,1889"/>
    </cell>
    <cell start-row="15" end-row="15" start-col="9" end-col="9">
      <Coords points="4010,1889 4010,2005 4749,1979 4749,1939 4748,1878"/>
    </cell>
    <cell start-row="16" end-row="16" start-col="0" end-col="0">
      <Coords points="34,1979 34,1983 36,2054 35,2071 171,2074 171,1976"/>
    </cell>
    <cell start-row="16" end-row="16" start-col="1" end-col="1">
      <Coords points="171,1976 171,2074 399,2079 399,1973"/>
    </cell>
    <cell start-row="16" end-row="16" start-col="2" end-col="2">
      <Coords points="399,1973 399,2079 478,2082 941,2092 1192,2102 1192,2015 862,2018 720,1996 503,1972"/>
    </cell>
    <cell start-row="16" end-row="16" start-col="3" end-col="3">
      <Coords points="1192,2015 1192,2102 1354,2109 1354,2013"/>
    </cell>
    <cell start-row="16" end-row="16" start-col="4" end-col="4">
      <Coords points="1354,2013 1354,2109 1627,2121 1844,2127 1844,2014 1565,2012"/>
    </cell>
    <cell start-row="16" end-row="16" start-col="5" end-col="5">
      <Coords points="1844,2014 1844,2127 2287,2134 2388,2145 2388,2019 2277,2019"/>
    </cell>
    <cell start-row="16" end-row="16" start-col="6" end-col="6">
      <Coords points="2388,2019 2388,2145 2467,2148 2576,2141 2774,2137 2975,2130 2974,2022"/>
    </cell>
    <cell start-row="16" end-row="16" start-col="7" end-col="7">
      <Coords points="2974,2022 2975,2130 3489,2112 3489,2018 3016,2023"/>
    </cell>
    <cell start-row="16" end-row="16" start-col="8" end-col="8">
      <Coords points="3489,2018 3489,2112 4010,2095 4010,2005 3720,2016"/>
    </cell>
    <cell start-row="16" end-row="16" start-col="9" end-col="9">
      <Coords points="4010,2005 4010,2095 4748,2071 4749,2065 4749,1979"/>
    </cell>
    <cell start-row="17" end-row="17" start-col="0" end-col="0">
      <Coords points="35,2071 32,2136 33,2193 170,2193 171,2074"/>
    </cell>
    <cell start-row="17" end-row="17" start-col="1" end-col="1">
      <Coords points="171,2074 170,2193 398,2194 399,2079"/>
    </cell>
    <cell start-row="17" end-row="17" start-col="2" end-col="2">
      <Coords points="399,2079 398,2194 573,2196 905,2201 1192,2208 1192,2102 941,2092 478,2082"/>
    </cell>
    <cell start-row="17" end-row="17" start-col="3" end-col="3">
      <Coords points="1192,2102 1192,2208 1353,2212 1354,2109"/>
    </cell>
    <cell start-row="17" end-row="17" start-col="4" end-col="4">
      <Coords points="1354,2109 1353,2212 1557,2218 1844,2224 1844,2127 1627,2121"/>
    </cell>
    <cell start-row="17" end-row="17" start-col="5" end-col="5">
      <Coords points="1844,2127 1844,2224 2174,2231 2388,2237 2388,2145 2287,2134"/>
    </cell>
    <cell start-row="17" end-row="17" start-col="6" end-col="6">
      <Coords points="2388,2145 2388,2237 2534,2242 2704,2239 2976,2232 2975,2130 2774,2137 2576,2141 2467,2148"/>
    </cell>
    <cell start-row="17" end-row="17" start-col="7" end-col="7">
      <Coords points="2975,2130 2976,2232 3491,2220 3489,2112"/>
    </cell>
    <cell start-row="17" end-row="17" start-col="8" end-col="8">
      <Coords points="3489,2112 3491,2220 4010,2208 4010,2095"/>
    </cell>
    <cell start-row="17" end-row="17" start-col="9" end-col="9">
      <Coords points="4010,2095 4010,2208 4743,2193 4743,2184 4745,2151 4748,2071"/>
    </cell>
    <cell start-row="18" end-row="18" start-col="0" end-col="0">
      <Coords points="33,2193 35,2246 34,2273 169,2274 170,2193"/>
    </cell>
    <cell start-row="18" end-row="18" start-col="1" end-col="1">
      <Coords points="170,2193 169,2274 396,2276 398,2194"/>
    </cell>
    <cell start-row="18" end-row="18" start-col="2" end-col="2">
      <Coords points="398,2194 396,2276 488,2277 664,2279 1191,2285 1192,2208 905,2201 573,2196"/>
    </cell>
    <cell start-row="18" end-row="18" start-col="3" end-col="3">
      <Coords points="1192,2208 1191,2285 1270,2286 1353,2288 1353,2212"/>
    </cell>
    <cell start-row="18" end-row="18" start-col="4" end-col="4">
      <Coords points="1353,2212 1353,2288 1584,2297 1844,2301 1844,2224 1557,2218"/>
    </cell>
    <cell start-row="18" end-row="18" start-col="5" end-col="5">
      <Coords points="1844,2224 1844,2301 2250,2309 2388,2307 2388,2237 2174,2231"/>
    </cell>
    <cell start-row="18" end-row="18" start-col="6" end-col="6">
      <Coords points="2388,2237 2388,2307 2697,2305 2976,2302 2976,2232 2704,2239 2534,2242"/>
    </cell>
    <cell start-row="18" end-row="18" start-col="7" end-col="7">
      <Coords points="2976,2232 2976,2302 3169,2301 3491,2295 3491,2220"/>
    </cell>
    <cell start-row="18" end-row="18" start-col="8" end-col="8">
      <Coords points="3491,2220 3491,2295 4011,2285 4010,2208"/>
    </cell>
    <cell start-row="18" end-row="18" start-col="9" end-col="9">
      <Coords points="4010,2208 4011,2285 4743,2273 4743,2193"/>
    </cell>
    <cell start-row="19" end-row="19" start-col="0" end-col="0">
      <Coords points="34,2273 32,2367 169,2366 169,2274"/>
    </cell>
    <cell start-row="19" end-row="19" start-col="1" end-col="1">
      <Coords points="169,2274 169,2366 395,2366 396,2276"/>
    </cell>
    <cell start-row="19" end-row="19" start-col="2" end-col="2">
      <Coords points="396,2276 395,2366 501,2366 619,2374 809,2384 1191,2391 1191,2285 664,2279 488,2277"/>
    </cell>
    <cell start-row="19" end-row="19" start-col="3" end-col="3">
      <Coords points="1191,2285 1191,2391 1353,2394 1353,2288 1270,2286"/>
    </cell>
    <cell start-row="19" end-row="19" start-col="4" end-col="4">
      <Coords points="1353,2288 1353,2394 1652,2400 1843,2404 1844,2301 1584,2297"/>
    </cell>
    <cell start-row="19" end-row="19" start-col="5" end-col="5">
      <Coords points="1844,2301 1843,2404 2315,2415 2388,2414 2388,2307 2250,2309"/>
    </cell>
    <cell start-row="19" end-row="19" start-col="6" end-col="6">
      <Coords points="2388,2307 2388,2414 2655,2412 2977,2405 2976,2302 2697,2305"/>
    </cell>
    <cell start-row="19" end-row="19" start-col="7" end-col="7">
      <Coords points="2976,2302 2977,2405 3493,2393 3491,2295 3169,2301"/>
    </cell>
    <cell start-row="19" end-row="19" start-col="8" end-col="8">
      <Coords points="3491,2295 3493,2393 4012,2382 4011,2285"/>
    </cell>
    <cell start-row="19" end-row="19" start-col="9" end-col="9">
      <Coords points="4011,2285 4012,2382 4743,2367 4743,2334 4743,2273"/>
    </cell>
    <cell start-row="20" end-row="20" start-col="0" end-col="0">
      <Coords points="32,2367 30,2470 166,2469 169,2366"/>
    </cell>
    <cell start-row="20" end-row="20" start-col="1" end-col="1">
      <Coords points="169,2366 166,2469 395,2467 395,2366"/>
    </cell>
    <cell start-row="20" end-row="20" start-col="2" end-col="2">
      <Coords points="395,2366 395,2467 583,2466 832,2486 1191,2491 1191,2391 809,2384 619,2374 501,2366"/>
    </cell>
    <cell start-row="20" end-row="20" start-col="3" end-col="3">
      <Coords points="1191,2391 1191,2491 1352,2493 1353,2394"/>
    </cell>
    <cell start-row="20" end-row="20" start-col="4" end-col="4">
      <Coords points="1353,2394 1352,2493 1843,2501 1843,2404 1652,2400"/>
    </cell>
    <cell start-row="20" end-row="20" start-col="5" end-col="5">
      <Coords points="1843,2404 1843,2501 2292,2510 2388,2508 2388,2414 2315,2415"/>
    </cell>
    <cell start-row="20" end-row="20" start-col="6" end-col="6">
      <Coords points="2388,2414 2388,2508 2643,2504 2746,2503 2978,2494 2977,2405 2655,2412"/>
    </cell>
    <cell start-row="20" end-row="20" start-col="7" end-col="7">
      <Coords points="2977,2405 2978,2494 3494,2475 3493,2393"/>
    </cell>
    <cell start-row="20" end-row="20" start-col="8" end-col="8">
      <Coords points="3493,2393 3494,2475 3831,2463 4012,2464 4012,2382"/>
    </cell>
    <cell start-row="20" end-row="20" start-col="9" end-col="9">
      <Coords points="4012,2382 4012,2464 4739,2470 4740,2454 4743,2429 4743,2367"/>
    </cell>
    <cell start-row="21" end-row="21" start-col="0" end-col="0">
      <Coords points="30,2470 30,2514 30,2568 165,2566 166,2469"/>
    </cell>
    <cell start-row="21" end-row="21" start-col="1" end-col="1">
      <Coords points="166,2469 165,2566 395,2564 395,2467"/>
    </cell>
    <cell start-row="21" end-row="21" start-col="2" end-col="2">
      <Coords points="395,2467 395,2564 689,2563 950,2564 1191,2566 1191,2491 832,2486 583,2466"/>
    </cell>
    <cell start-row="21" end-row="21" start-col="3" end-col="3">
      <Coords points="1191,2491 1191,2566 1352,2567 1352,2493"/>
    </cell>
    <cell start-row="21" end-row="21" start-col="4" end-col="4">
      <Coords points="1352,2493 1352,2567 1541,2569 1842,2582 1843,2501"/>
    </cell>
    <cell start-row="21" end-row="21" start-col="5" end-col="5">
      <Coords points="1843,2501 1842,2582 2388,2606 2388,2508 2292,2510"/>
    </cell>
    <cell start-row="21" end-row="21" start-col="6" end-col="6">
      <Coords points="2388,2508 2388,2606 2506,2612 2715,2590 2978,2591 2978,2494 2746,2503 2643,2504"/>
    </cell>
    <cell start-row="21" end-row="21" start-col="7" end-col="7">
      <Coords points="2978,2494 2978,2591 3027,2592 3494,2585 3494,2475"/>
    </cell>
    <cell start-row="21" end-row="21" start-col="8" end-col="8">
      <Coords points="3494,2475 3494,2585 4013,2577 4012,2464 3831,2463"/>
    </cell>
    <cell start-row="21" end-row="21" start-col="9" end-col="9">
      <Coords points="4012,2464 4013,2577 4738,2568 4738,2527 4739,2470"/>
    </cell>
    <cell start-row="22" end-row="22" start-col="0" end-col="0">
      <Coords points="30,2568 31,2660 166,2660 165,2566"/>
    </cell>
    <cell start-row="22" end-row="22" start-col="1" end-col="1">
      <Coords points="165,2566 166,2660 395,2660 395,2564"/>
    </cell>
    <cell start-row="22" end-row="22" start-col="2" end-col="2">
      <Coords points="395,2564 395,2660 628,2661 918,2668 996,2668 1190,2670 1191,2566 950,2564 689,2563"/>
    </cell>
    <cell start-row="22" end-row="22" start-col="3" end-col="3">
      <Coords points="1191,2566 1190,2670 1352,2672 1352,2567"/>
    </cell>
    <cell start-row="22" end-row="22" start-col="4" end-col="4">
      <Coords points="1352,2567 1352,2672 1498,2675 1842,2686 1842,2582 1541,2569"/>
    </cell>
    <cell start-row="22" end-row="22" start-col="5" end-col="5">
      <Coords points="1842,2582 1842,2686 2387,2704 2388,2606"/>
    </cell>
    <cell start-row="22" end-row="22" start-col="6" end-col="6">
      <Coords points="2388,2606 2387,2704 2486,2708 2873,2690 2979,2688 2978,2591 2715,2590 2506,2612"/>
    </cell>
    <cell start-row="22" end-row="22" start-col="7" end-col="7">
      <Coords points="2978,2591 2979,2688 3494,2679 3494,2585 3027,2592"/>
    </cell>
    <cell start-row="22" end-row="22" start-col="8" end-col="8">
      <Coords points="3494,2585 3494,2679 4014,2671 4013,2577"/>
    </cell>
    <cell start-row="22" end-row="22" start-col="9" end-col="9">
      <Coords points="4013,2577 4014,2671 4738,2660 4738,2568"/>
    </cell>
    <cell start-row="23" end-row="23" start-col="0" end-col="0">
      <Coords points="31,2660 32,2757 166,2756 166,2660"/>
    </cell>
    <cell start-row="23" end-row="23" start-col="1" end-col="1">
      <Coords points="166,2660 166,2756 394,2756 395,2660"/>
    </cell>
    <cell start-row="23" end-row="23" start-col="2" end-col="2">
      <Coords points="395,2660 394,2756 760,2756 931,2758 1190,2766 1190,2670 996,2668 918,2668 628,2661"/>
    </cell>
    <cell start-row="23" end-row="23" start-col="3" end-col="3">
      <Coords points="1190,2670 1190,2766 1352,2771 1352,2672"/>
    </cell>
    <cell start-row="23" end-row="23" start-col="4" end-col="4">
      <Coords points="1352,2672 1352,2771 1842,2787 1842,2686 1498,2675"/>
    </cell>
    <cell start-row="23" end-row="23" start-col="5" end-col="5">
      <Coords points="1842,2686 1842,2787 2387,2804 2387,2704"/>
    </cell>
    <cell start-row="23" end-row="23" start-col="6" end-col="6">
      <Coords points="2387,2704 2387,2804 2574,2811 2980,2800 2979,2688 2873,2690 2486,2708"/>
    </cell>
    <cell start-row="23" end-row="23" start-col="7" end-col="7">
      <Coords points="2979,2688 2980,2800 3495,2787 3494,2679"/>
    </cell>
    <cell start-row="23" end-row="23" start-col="8" end-col="8">
      <Coords points="3494,2679 3495,2787 4014,2774 4014,2671"/>
    </cell>
    <cell start-row="23" end-row="23" start-col="9" end-col="9">
      <Coords points="4014,2671 4014,2774 4738,2757 4738,2660"/>
    </cell>
    <cell start-row="24" end-row="24" start-col="0" end-col="0">
      <Coords points="32,2757 33,2758 33,2863 166,2863 166,2756"/>
    </cell>
    <cell start-row="24" end-row="24" start-col="1" end-col="1">
      <Coords points="166,2756 166,2863 394,2863 394,2756"/>
    </cell>
    <cell start-row="24" end-row="24" start-col="2" end-col="2">
      <Coords points="394,2756 394,2863 626,2864 853,2866 1111,2869 1190,2870 1190,2766 931,2758 760,2756"/>
    </cell>
    <cell start-row="24" end-row="24" start-col="3" end-col="3">
      <Coords points="1190,2766 1190,2870 1351,2872 1352,2771"/>
    </cell>
    <cell start-row="24" end-row="24" start-col="4" end-col="4">
      <Coords points="1352,2771 1351,2872 1554,2876 1842,2878 1842,2787"/>
    </cell>
    <cell start-row="24" end-row="24" start-col="5" end-col="5">
      <Coords points="1842,2787 1842,2878 2324,2883 2386,2885 2387,2804"/>
    </cell>
    <cell start-row="24" end-row="24" start-col="6" end-col="6">
      <Coords points="2387,2804 2386,2885 2638,2898 2980,2892 2980,2800 2574,2811"/>
    </cell>
    <cell start-row="24" end-row="24" start-col="7" end-col="7">
      <Coords points="2980,2800 2980,2892 3495,2883 3495,2787"/>
    </cell>
    <cell start-row="24" end-row="24" start-col="8" end-col="8">
      <Coords points="3495,2787 3495,2883 4014,2874 4014,2774"/>
    </cell>
    <cell start-row="24" end-row="24" start-col="9" end-col="9">
      <Coords points="4014,2774 4014,2874 4739,2863 4739,2771 4738,2757"/>
    </cell>
    <cell start-row="25" end-row="25" start-col="0" end-col="0">
      <Coords points="33,2863 33,2960 165,2956 166,2863"/>
    </cell>
    <cell start-row="25" end-row="25" start-col="1" end-col="1">
      <Coords points="166,2863 165,2956 394,2951 394,2863"/>
    </cell>
    <cell start-row="25" end-row="25" start-col="2" end-col="2">
      <Coords points="394,2863 394,2951 463,2950 680,2966 918,2968 1121,2981 1189,2979 1190,2870 1111,2869 853,2866 626,2864"/>
    </cell>
    <cell start-row="25" end-row="25" start-col="3" end-col="3">
      <Coords points="1190,2870 1189,2979 1351,2974 1351,2872"/>
    </cell>
    <cell start-row="25" end-row="25" start-col="4" end-col="4">
      <Coords points="1351,2872 1351,2974 1560,2969 1843,2969 1842,2878 1554,2876"/>
    </cell>
    <cell start-row="25" end-row="25" start-col="5" end-col="5">
      <Coords points="1842,2878 1843,2969 2351,2970 2386,2969 2386,2885 2324,2883"/>
    </cell>
    <cell start-row="25" end-row="25" start-col="6" end-col="6">
      <Coords points="2386,2885 2386,2969 2981,2966 2980,2892 2638,2898"/>
    </cell>
    <cell start-row="25" end-row="25" start-col="7" end-col="7">
      <Coords points="2980,2892 2981,2966 3496,2964 3495,2883"/>
    </cell>
    <cell start-row="25" end-row="25" start-col="8" end-col="8">
      <Coords points="3495,2883 3496,2964 4014,2962 4014,2874"/>
    </cell>
    <cell start-row="25" end-row="25" start-col="9" end-col="9">
      <Coords points="4014,2874 4014,2962 4739,2960 4739,2863"/>
    </cell>
    <cell start-row="26" end-row="26" start-col="0" end-col="0">
      <Coords points="33,2960 34,3040 33,3045 165,3045 165,2956"/>
    </cell>
    <cell start-row="26" end-row="26" start-col="1" end-col="1">
      <Coords points="165,2956 165,3045 394,3045 394,2951"/>
    </cell>
    <cell start-row="26" end-row="26" start-col="2" end-col="2">
      <Coords points="394,2951 394,3045 609,3045 752,3054 1115,3083 1189,3082 1189,2979 1121,2981 918,2968 680,2966 463,2950"/>
    </cell>
    <cell start-row="26" end-row="26" start-col="3" end-col="3">
      <Coords points="1189,2979 1189,3082 1351,3080 1351,2974"/>
    </cell>
    <cell start-row="26" end-row="26" start-col="4" end-col="4">
      <Coords points="1351,2974 1351,3080 1843,3074 1843,2969 1560,2969"/>
    </cell>
    <cell start-row="26" end-row="26" start-col="5" end-col="5">
      <Coords points="1843,2969 1843,3074 2308,3069 2386,3069 2386,2969 2351,2970"/>
    </cell>
    <cell start-row="26" end-row="26" start-col="6" end-col="6">
      <Coords points="2386,2969 2386,3069 2670,3070 2981,3066 2981,2966"/>
    </cell>
    <cell start-row="26" end-row="26" start-col="7" end-col="7">
      <Coords points="2981,2966 2981,3066 3496,3059 3496,2964"/>
    </cell>
    <cell start-row="26" end-row="26" start-col="8" end-col="8">
      <Coords points="3496,2964 3496,3059 4013,3053 4014,2962"/>
    </cell>
    <cell start-row="26" end-row="26" start-col="9" end-col="9">
      <Coords points="4014,2962 4013,3053 4739,3045 4739,2964 4739,2960"/>
    </cell>
    <cell start-row="27" end-row="27" start-col="0" end-col="0">
      <Coords points="33,3045 32,3159 166,3159 165,3045"/>
    </cell>
    <cell start-row="27" end-row="27" start-col="1" end-col="1">
      <Coords points="165,3045 166,3159 393,3159 394,3045"/>
    </cell>
    <cell start-row="27" end-row="27" start-col="2" end-col="2">
      <Coords points="394,3045 393,3159 1188,3160 1189,3082 1115,3083 752,3054 609,3045"/>
    </cell>
    <cell start-row="27" end-row="27" start-col="3" end-col="3">
      <Coords points="1189,3082 1188,3160 1351,3160 1351,3080"/>
    </cell>
    <cell start-row="27" end-row="27" start-col="4" end-col="4">
      <Coords points="1351,3080 1351,3160 1545,3161 1843,3159 1843,3074"/>
    </cell>
    <cell start-row="27" end-row="27" start-col="5" end-col="5">
      <Coords points="1843,3074 1843,3159 2340,3158 2386,3166 2386,3069 2308,3069"/>
    </cell>
    <cell start-row="27" end-row="27" start-col="6" end-col="6">
      <Coords points="2386,3069 2386,3166 2468,3181 2795,3174 2981,3172 2981,3066 2670,3070"/>
    </cell>
    <cell start-row="27" end-row="27" start-col="7" end-col="7">
      <Coords points="2981,3066 2981,3172 3497,3168 3496,3059"/>
    </cell>
    <cell start-row="27" end-row="27" start-col="8" end-col="8">
      <Coords points="3496,3059 3497,3168 4013,3164 4013,3053"/>
    </cell>
    <cell start-row="27" end-row="27" start-col="9" end-col="9">
      <Coords points="4013,3053 4013,3164 4738,3159 4739,3120 4739,3045"/>
    </cell>
    <cell start-row="28" end-row="28" start-col="0" end-col="0">
      <Coords points="32,3159 32,3263 31,3265 164,3267 166,3159"/>
    </cell>
    <cell start-row="28" end-row="28" start-col="1" end-col="1">
      <Coords points="166,3159 164,3267 260,3269 392,3265 393,3159"/>
    </cell>
    <cell start-row="28" end-row="28" start-col="2" end-col="2">
      <Coords points="393,3159 392,3265 466,3263 672,3262 1187,3284 1188,3160"/>
    </cell>
    <cell start-row="28" end-row="28" start-col="3" end-col="3">
      <Coords points="1188,3160 1187,3284 1350,3291 1351,3160"/>
    </cell>
    <cell start-row="28" end-row="28" start-col="4" end-col="4">
      <Coords points="1351,3160 1350,3291 1432,3295 1842,3284 1843,3159 1545,3161"/>
    </cell>
    <cell start-row="28" end-row="28" start-col="5" end-col="5">
      <Coords points="1843,3159 1842,3284 2385,3269 2386,3166 2340,3158"/>
    </cell>
    <cell start-row="28" end-row="28" start-col="6" end-col="6">
      <Coords points="2386,3166 2385,3269 2516,3266 2981,3265 2981,3172 2795,3174 2468,3181"/>
    </cell>
    <cell start-row="28" end-row="28" start-col="7" end-col="7">
      <Coords points="2981,3172 2981,3265 3497,3265 3497,3168"/>
    </cell>
    <cell start-row="28" end-row="28" start-col="8" end-col="8">
      <Coords points="3497,3168 3497,3265 4013,3265 4013,3164"/>
    </cell>
    <cell start-row="28" end-row="28" start-col="9" end-col="9">
      <Coords points="4013,3164 4013,3265 4737,3265 4738,3159"/>
    </cell>
    <cell start-row="29" end-row="29" start-col="0" end-col="0">
      <Coords points="31,3265 31,3379 163,3378 164,3267"/>
    </cell>
    <cell start-row="29" end-row="29" start-col="1" end-col="1">
      <Coords points="164,3267 163,3378 391,3376 392,3265 260,3269"/>
    </cell>
    <cell start-row="29" end-row="29" start-col="2" end-col="2">
      <Coords points="392,3265 391,3376 1187,3372 1187,3284 672,3262 466,3263"/>
    </cell>
    <cell start-row="29" end-row="29" start-col="3" end-col="3">
      <Coords points="1187,3284 1187,3372 1350,3371 1350,3291"/>
    </cell>
    <cell start-row="29" end-row="29" start-col="4" end-col="4">
      <Coords points="1350,3291 1350,3371 1842,3369 1842,3284 1432,3295"/>
    </cell>
    <cell start-row="29" end-row="29" start-col="5" end-col="5">
      <Coords points="1842,3284 1842,3369 2385,3366 2385,3269"/>
    </cell>
    <cell start-row="29" end-row="29" start-col="6" end-col="6">
      <Coords points="2385,3269 2385,3366 2982,3364 2981,3265 2516,3266"/>
    </cell>
    <cell start-row="29" end-row="29" start-col="7" end-col="7">
      <Coords points="2981,3265 2982,3364 3497,3362 3497,3265"/>
    </cell>
    <cell start-row="29" end-row="29" start-col="8" end-col="8">
      <Coords points="3497,3265 3497,3362 3737,3362 4013,3366 4013,3265"/>
    </cell>
    <cell start-row="29" end-row="29" start-col="9" end-col="9">
      <Coords points="4013,3265 4013,3366 4737,3379 4737,3311 4737,3265"/>
    </cell>
    <cell start-row="30" end-row="30" start-col="0" end-col="0">
      <Coords points="31,3379 31,3415 31,3476 162,3475 163,3378"/>
    </cell>
    <cell start-row="30" end-row="30" start-col="1" end-col="1">
      <Coords points="163,3378 162,3475 390,3474 391,3376"/>
    </cell>
    <cell start-row="30" end-row="30" start-col="2" end-col="2">
      <Coords points="391,3376 390,3474 831,3474 1187,3484 1187,3372"/>
    </cell>
    <cell start-row="30" end-row="30" start-col="3" end-col="3">
      <Coords points="1187,3372 1187,3484 1349,3488 1350,3371"/>
    </cell>
    <cell start-row="30" end-row="30" start-col="4" end-col="4">
      <Coords points="1350,3371 1349,3488 1551,3495 1841,3493 1842,3369"/>
    </cell>
    <cell start-row="30" end-row="30" start-col="5" end-col="5">
      <Coords points="1842,3369 1841,3493 2384,3489 2385,3366"/>
    </cell>
    <cell start-row="30" end-row="30" start-col="6" end-col="6">
      <Coords points="2385,3366 2384,3489 2983,3485 2982,3364"/>
    </cell>
    <cell start-row="30" end-row="30" start-col="7" end-col="7">
      <Coords points="2982,3364 2983,3485 3497,3482 3497,3362"/>
    </cell>
    <cell start-row="30" end-row="30" start-col="8" end-col="8">
      <Coords points="3497,3362 3497,3482 4014,3479 4013,3366 3737,3362"/>
    </cell>
    <cell start-row="30" end-row="30" start-col="9" end-col="9">
      <Coords points="4013,3366 4014,3479 4737,3476 4737,3379"/>
    </cell>
    <cell start-row="31" end-row="31" start-col="0" end-col="0">
      <Coords points="31,3476 31,3568 160,3567 162,3475"/>
    </cell>
    <cell start-row="31" end-row="31" start-col="1" end-col="1">
      <Coords points="162,3475 160,3567 390,3566 390,3474"/>
    </cell>
    <cell start-row="31" end-row="31" start-col="2" end-col="2">
      <Coords points="390,3474 390,3566 492,3566 753,3577 1186,3596 1187,3484 831,3474"/>
    </cell>
    <cell start-row="31" end-row="31" start-col="3" end-col="3">
      <Coords points="1187,3484 1186,3596 1254,3600 1348,3596 1349,3488"/>
    </cell>
    <cell start-row="31" end-row="31" start-col="4" end-col="4">
      <Coords points="1349,3488 1348,3596 1460,3593 1781,3595 1840,3594 1841,3493 1551,3495"/>
    </cell>
    <cell start-row="31" end-row="31" start-col="5" end-col="5">
      <Coords points="1841,3493 1840,3594 2384,3589 2384,3489"/>
    </cell>
    <cell start-row="31" end-row="31" start-col="6" end-col="6">
      <Coords points="2384,3489 2384,3589 2984,3583 2983,3485"/>
    </cell>
    <cell start-row="31" end-row="31" start-col="7" end-col="7">
      <Coords points="2983,3485 2984,3583 3497,3578 3497,3482"/>
    </cell>
    <cell start-row="31" end-row="31" start-col="8" end-col="8">
      <Coords points="3497,3482 3497,3578 4015,3573 4014,3479"/>
    </cell>
    <cell start-row="31" end-row="31" start-col="9" end-col="9">
      <Coords points="4014,3479 4015,3573 4737,3568 4737,3476"/>
    </cell>
    <cell start-row="32" end-row="32" start-col="0" end-col="0">
      <Coords points="31,3568 32,3744 55,3783 69,3828 158,3828 160,3567"/>
    </cell>
    <cell start-row="32" end-row="32" start-col="1" end-col="1">
      <Coords points="160,3567 158,3828 319,3828 388,3826 390,3566"/>
    </cell>
    <cell start-row="32" end-row="32" start-col="2" end-col="2">
      <Coords points="390,3566 388,3826 491,3825 698,3828 836,3832 914,3832 972,3829 1073,3830 1183,3830 1186,3596 753,3577 492,3566"/>
    </cell>
    <cell start-row="32" end-row="32" start-col="3" end-col="3">
      <Coords points="1186,3596 1183,3830 1317,3832 1345,3831 1348,3596 1254,3600"/>
    </cell>
    <cell start-row="32" end-row="32" start-col="4" end-col="4">
      <Coords points="1348,3596 1345,3831 1516,3831 1569,3833 1667,3833 1797,3834 1837,3834 1840,3594 1781,3595 1460,3593"/>
    </cell>
    <cell start-row="32" end-row="32" start-col="5" end-col="5">
      <Coords points="1840,3594 1837,3834 1875,3834 1918,3839 2084,3843 2241,3844 2295,3845 2363,3844 2383,3840 2384,3589"/>
    </cell>
    <cell start-row="32" end-row="32" start-col="6" end-col="6">
      <Coords points="2384,3589 2383,3840 2398,3844 2501,3844 2586,3844 2621,3844 2677,3846 2797,3844 2867,3843 2897,3843 2918,3848 2940,3846 2984,3848 2984,3583"/>
    </cell>
    <cell start-row="32" end-row="32" start-col="7" end-col="7">
      <Coords points="2984,3583 2984,3848 3023,3850 3121,3850 3201,3848 3276,3845 3383,3844 3496,3843 3497,3578"/>
    </cell>
    <cell start-row="32" end-row="32" start-col="8" end-col="8">
      <Coords points="3497,3578 3496,3843 3515,3843 3611,3848 3837,3850 4017,3851 4015,3573"/>
    </cell>
    <cell start-row="32" end-row="32" start-col="9" end-col="9">
      <Coords points="4015,3573 4017,3851 4093,3852 4444,3856 4712,3854 4720,3834 4729,3816 4733,3794 4735,3745 4738,3605 4737,3568"/>
    </cell>
  </table>
</document>
